MANIFEST.in
README.md
Wikipedia to Named Entity Recognition.ipynb
setup.py
wikipedia_ner/__init__.py
wikipedia_ner.egg-info/PKG-INFO
wikipedia_ner.egg-info/SOURCES.txt
wikipedia_ner.egg-info/dependency_links.txt
wikipedia_ner.egg-info/not-zip-safe
wikipedia_ner.egg-info/requires.txt
wikipedia_ner.egg-info/top_level.txt
wikipedia_ner/parse/__init__.py
wikipedia_ner/parse/dump_result.py
wikipedia_ner/parse/parse.py
wikipedia_ner/parse/parsed_page.py
wikipedia_ner/parse/sqlite_utils.py
wikipedia_ner/parse/utils.py
wikipedia_ner/parse/pages/__init__.py
wikipedia_ner/parse/pages/parsed_page.py
wikipedia_ner/parse/pages/parsed_page_child.py
wikipedia_ner/parse/pages/parsed_page_parent.py
wikipedia_ner/parse/sqlite_proto_buff/__init__.py
wikipedia_ner/parse/sqlite_proto_buff/corpus_pb2.py