Metadata-Version: 1.1
Name: wikipedia-ner
Version: 0.0.22
Summary: Python package for creating labeled examples from wiki dumps
Home-page: https://github.com/JonathanRaiman/wikipedia_ner
Author: Jonathan Raiman
Author-email: jraiman at mit dot edu
License: MIT
Download-URL: https://github.com/JonathanRaiman/wikipedia_ner
Keywords: XML,epub,tokenization,NLP
Platform: any
Classifier: Intended Audience :: Science/Research
Classifier: Operating System :: OS Independent
Classifier: Programming Language :: Python :: 3.3
Classifier: Topic :: Text Processing :: Linguistic
